{"name": "Almejita", "job": "Estrella de Twitch", "img": null, "birth_date": ["2", "1,", "1997"], "birth_place": "Espa\u00f1a", "about": "Streamer conocido por. Rust, Counter-Strike, y Dark and Darker. Dijo que aunque puede que no sea el \"m\u00e1s pro\" en los juegos, siempre le echa ganas. Ha juntado m\u00e1s de 160.000 seguidores en su almejita___ cuenta de Twitch.", "before_fame": "Se uni\u00f3 a YouTube en octubre de 2015.", "curiosities": "En YouTube, comparti\u00f3 su reacci\u00f3n a la colaboraci\u00f3n musical de Shakira y Bizarrap. Tambi\u00e9n est\u00e1 activo en TikTok, donde ha acumulado m\u00e1s de 460.000 me gusta en sus videos.", "family_life": "\u00c9l es de Espa\u00f1a.", "association": "Subi\u00f3 un video sobre una pelea de 2023 entre Samy Rivers y Mayichi."}