{"name": "Athena Nicole Grey", "job": "Estrella de Instagram", "img": "https://www.famousbirthdays.com/faces/grey-athena-image.jpg", "birth_date": ["6", "2,", "1964"], "birth_place": "Ciudad de Nueva York,  NY", "about": "Popular en Instagram con m\u00e1s de 20.000 seguidores. Comparte fotos de su vida cotidiana al igual que bellos paisajes y fotos de caballos; trabaja como editora, modelo, estilista de fotos, ecuestre y emprendedora.", "before_fame": "Ha montado a caballo desde que ten\u00eda seis a\u00f1os. Recibi\u00f3 su licenciatura del American College of Greece.", "curiosities": "Extendi\u00e9ndose de costa a costa, ha sido due\u00f1a de nueve tiendas de lujos llamadas Nicole Grey and Co.", "family_life": "Est\u00e1 radicada en San Francisco y Nueva York. Suele publicar fotos de su perro en Instagram.", "association": "Fue una productora ejecutiva de la pel\u00edcula Bereave en donde actu\u00f3\u00a0Malcolm McDowell."}