{"name": "Courtney B. Vance", "job": "Actor de Televisi\u00f3n", "img": "https://www.famousbirthdays.com/faces/vance-courtney-image.jpg", "birth_date": ["3", "12,", "1960"], "birth_place": "Detroit,  MI", "about": "Interpret\u00f3 el papel de Ron Carver en la serie de televisi\u00f3n\u00a0Law & Order: Criminal Intent\u00a0y que apareci\u00f3 como invitado en\u00a0The Closer\u00a0de TNT. En el 2016 gan\u00f3 un premio Emmy por su interpretaci\u00f3n de Johnnie Cochran en la serie limitada The People v. O.J. Simpson: American Crime Story de FX.", "before_fame": "Se gradu\u00f3 de la Universidad Harvard y trabaj\u00f3 como actor en la Compa\u00f1\u00eda de Shakespeare de Boston.", "curiosities": "Obtuvo dos nominaciones al premio Tony por sus papeles en Fences y Six Degrees of Separation. Interpret\u00f3 a Marshall en la serie de televisi\u00f3n del 2024 Grotesquerie.", "family_life": "Se cas\u00f3 con\u00a0Angela Bassett\u00a0en 1997 y tuvieron mellizos llamados Bronwyn y Slater.", "association": "Apareci\u00f3 en Space Cowboys (2000) de\u00a0Clint Eastwood."}