{"name": "Cristina Porta Acosta", "job": "Presentador de Programas de TV", "img": null, "birth_date": ["7", "4,", "1990"], "birth_place": "Espa\u00f1a", "about": "Periodista deportiva que cubri\u00f3 la Copa Mundial de la FIFA 2018. Ha presentado programas para las cadenas de televisi\u00f3n espa\u00f1olas La Sexta y Mega. En el 2021, fue concursante de la primera temporada del programa de telerrealidad Secret Story.", "before_fame": "Es licenciada en Periodismo, Publicidad y Relaciones P\u00fablicas por la Universidad Rovira i Virgili.", "curiosities": "Trabaj\u00f3 como redactora de investigaci\u00f3n en el programa S\u00e1lvame. Publica fotos suyas en su cuenta de Instagram, cristiporta, donde ha conseguido m\u00e1s de 300.000 seguidores.", "family_life": "Est\u00e1 muy unida a su sobrino, que ha aparecido ocasionalmente en su cuenta de Instagram.", "association": "Ha entrevistado a celebridades como\u00a0Ricky Martin,\u00a0Sylvester Stallone\u00a0y\u00a0Antonio Banderas."}