{"name": "Fer Realpe", "job": "Estrella de TikTok", "img": "https://www.famousbirthdays.com/faces/realpe-fer-image.jpg", "birth_date": ["11", "4,", "1999"], "birth_place": "Colombia", "about": "Personalidad colombiana de TikTok conocida por su contenido de baile. En sus TikToks aparecen\u00a0KALEB DI MASI,\u00a0Naian Seani\u00a0y Michael Sembello.", "before_fame": "Lanz\u00f3 su cuenta en enero del 2021.", "curiosities": "En sus TikToks aparecen temas como \"Mi T\u00edo Snoop\" de\u00a0Alem\u00e1n\u00a0y \"Siempre T\u00fa\" de Grecia y Callejo. Tambi\u00e9n es activa en su cuenta de Instagram fer.realpe. El 5 de julio del 2022 public\u00f3 fotos para celebrar el mes del orgullo.", "family_life": "Ella y su novio han colaborado en videos de baile.\u00a0", "association": "Ella y Julia Slater son dos populares estrellas de TikTok que publican contenidos de baile."}