{"name": "Javiera Mena", "job": "Cantante Pop", "img": "https://www.famousbirthdays.com/faces/mena-javiera-image.jpg", "birth_date": ["6", "3,", "1983"], "birth_place": "Chile", "about": "M\u00fasico chilena de electropop que obtuvo reconocimiento internacional gracias a sencillos como \"Al Siguiente Nivel\" que fue nombrado el mejor sencillo del 2000 por Club Fonograma. \u00c9ste le otorg\u00f3 tambi\u00e9n a su segundo \u00e1lbum, Mena, la calificaci\u00f3n perfecto 100, la primera en la historia de la p\u00e1gina de internet.", "before_fame": "Toc\u00f3 en su primer concierto en la Universidad de Chile a los 17 a\u00f1os. \nFue luego miembro del d\u00fao Prissa desde el 2003 hasta el 2006.", "curiosities": "Su \u00e1lbum Mena fue nombrado \u00c1lbum Revelaci\u00f3n en el 2010 por iTunes M\u00e9xico.", "family_life": "Tiene un hermano llamado Gonzalo.", "association": "En el 2013 particip\u00f3 en la canci\u00f3n de Julieta Venegas\u00a0\"Vuelve.\""}