{"name": "Javier Sol\u00eds", "job": "Cantante de M\u00fasica Mundial", "img": "https://www.famousbirthdays.com/faces/solis-javier-image.jpg", "birth_date": ["9", "1,", "1931"], "birth_place": "M\u00e9xico", "about": "Cantante y actor mexicano mejor conocido por sus canciones de estilo bolero-ranchera.", "before_fame": "Naci\u00f3 bajo el nombre de Gabriel Siria Levario, hijo de padre carnicero y madre comerciante, pero fue criado principalmente por sus t\u00edos.", "curiosities": "Muri\u00f3 a la temprana edad de treinta y cuatro a\u00f1os despu\u00e9s de una cirug\u00eda de ves\u00edcula biliar fallida.", "family_life": "Estuvo casado con Blanca Estela Saenz, una bailarina que conoci\u00f3 en la Ciudad de M\u00e9xico.", "association": "El actor\u00a0Pedro Infante\u00a0y \u00e9l eran miembros de un destacado grupo de artistas mexicanos conocidos como \"Los Tres Gallos\".\u00a0"}