{"name": "JoaquinPutoAmo", "job": "Estrella de YouTube", "img": "https://www.famousbirthdays.com/faces/joaquinputoamo-image.jpg", "birth_date": ["8", "3,", "1994"], "birth_place": "Espa\u00f1a", "about": "Personalidad espa\u00f1ola de YouTube ampliamente conocido por su canal JoaquinPutoAmo. Ha acumulado m\u00e1s de [YCVYVC] reproducciones por sus desaf\u00edos extremos y etiquetados de amigos.", "before_fame": "Comenz\u00f3 con su canal de YouTube el 22 de enero del 2010.", "curiosities": "Ha acumulado m\u00e1s de 900.000 suscriptores en su canal de YouTube. Adem\u00e1s, ha conseguido m\u00e1s de 380.000 seguidores en su cuenta de Instagram joaquinputoam0.", "family_life": "Ha presentado a su padre en su canal de YouTube.", "association": "Ha colaborado con el tambi\u00e9n destacado YouTuber Jordi Wild en su canal de YouTube JoaquinPutoAmo."}