{"name": "Omar Murillo", "job": "Actor de Televisi\u00f3n", "img": null, "birth_date": ["10", "1,", "1981"], "birth_place": "Cali,Colombia", "about": "Actor ganador del Premio India Catalina mejor conocido por su trabajo en la telenovela colombiana LA SELECC1\u00d3N.\u00a0", "before_fame": "Debut\u00f3 en la televisi\u00f3n en el 2003 en la telenovela\u00a0Pasi\u00f3n de Gavilanes.", "curiosities": "Fue nominado a dos premios TVyNovelas consecutivos, en el 2014 y en el 2015.", "family_life": "Se cas\u00f3 con una mujer llamada Koral Costa.", "association": "Form\u00f3 parte del elenco de LA SELECC1\u00d3N, una serie tributo a la estrella de f\u00fatbol\u00a0Faustino Asprilla.\u00a0"}