{"name": "Pablo Cruz Guerrero", "job": "Actor de Televisi\u00f3n", "img": null, "birth_date": ["2", "2,", "1984"], "birth_place": "Ciudad de M\u00e9xico,M\u00e9xico", "about": "Actor que ha conseguido fama por su carrera en el cine y la TV mexicana, incluyendo como Felipe Alarc\u00f3n en la telenovela El Hotel de los Secretos en el 2016. Apareci\u00f3 en la telenovela Por Siempre Mi Amor de Televisa en el 2013-2014 como Daniel Cervantes.", "before_fame": "Hizo su debut televisivo en el 2007 en la serie \u00bfY ahora qu\u00e9 hago?", "curiosities": "Interpret\u00f3 a Daniel en la telenovela Cuando Me Enamoro del 2010. Apareci\u00f3 en la comedia rom\u00e1ntica Milagro en Praga.", "family_life": "Es originario de Ciudad de M\u00e9xico, M\u00e9xico.", "association": "Apareci\u00f3 junto a\u00a0Camilla Belle\u00a0en la pel\u00edcula From Prada to Nada del 2011."}