{"name": "Rade", "job": "Rapero", "img": "https://www.famousbirthdays.com/faces/rade-image.jpg", "birth_date": ["5", "2,", "1995"], "birth_place": "Espa\u00f1a", "about": "Rapero espa\u00f1ol que es la mitad del d\u00fao\u00a0OcerYRade, conocido por canciones como \"Por Nosotros,\" \"Aprend\u00ed\" y \"Sonr\u00edo.\"", "before_fame": "Ocer y \u00e9l se comenzaron a crear m\u00fasica juntos cuando a\u00fan estaban en la escuela.", "curiosities": "Lanzaron su primer \u00e1lbum, Alivi\u00e1ndome, en YouTube en el 2012.", "family_life": "Naci\u00f3 en Espa\u00f1a el 2 de mayo de 1995.", "association": "Dante AC\u00a0tambi\u00e9n es la mitad de un d\u00fao de rap espa\u00f1ol."}