{"name": "Abraham Rodriguez", "job": "Actor de Televisi\u00f3n", "img": "https://www.famousbirthdays.com/faces/rodriguez-abraham-image.jpg", "birth_date": ["1", "4,", "2000"], "birth_place": "Estados Unidos", "about": "Actor de televisi\u00f3n que es mejor reconocido por haber conseguido el papel de Nate Silva/Gold Ranger en\u00a0Power Rangers Beast Morphers. Esta exposici\u00f3n le ayud\u00f3 a conseguir m\u00e1s de 60.000 seguidores en Instagram.", "before_fame": "En el 2015 hizo una aparici\u00f3n en My Urban Teenage Trauma.", "curiosities": "Apareci\u00f3 como invitado en un episodio del 2018 de\u00a0Tosh.0.", "family_life": "Naci\u00f3 en Estados Unidos.", "association": "Apareci\u00f3 junto a\u00a0Jasmeet Baduwalia\u00a0en Power Rangers Beast Morphers."}