{"name": "Ansley Minor", "job": "Estrella de TikTok", "img": "https://www.famousbirthdays.com/faces/minor-ansley-image.jpg", "birth_date": ["1", "27", "2002"], "birth_place": "Estados Unidos", "about": "Estrella de las redes sociales que ha conseguido fama por su canal de TikTok ansleyyminor. Ha conseguido popularidad por sus montajes musicales y sus skits, frecuentemente centrados en las citas.\u00a0Se ha asociado con la marca Fashion Nova.", "before_fame": "Comenz\u00f3 su canal de TikTok en julio del 2019.", "curiosities": "Ha crecido a m\u00e1s de 1.3 millones de fan\u00e1ticos en TikTok. Frecuentemente ha modelado en cuenta de Instagram ansleyyminor.\u00a0Ha asistido a la Universidad de Clemson en Carolina del Sur.", "family_life": "Tiene una hermana llamada\u00a0Eliza. Tambi\u00e9n tiene dos hermanos.", "association": "En mayo del 2020, public\u00f3 una foto en Instagram junto a\u00a0Riley Hubatka."}