{"name": "Carla Adell", "job": "Actriz de Cine", "img": "https://www.famousbirthdays.com/faces/adell-carla-image.jpg", "birth_date": ["2", "18", "1998"], "birth_place": "M\u00e9xico", "about": "Actriz, modelo e influenciadora de las redes sociales que interpret\u00f3 a Laura en\u00a0No Manches Frida\u00a0y No Manches Frida 2. Otros de sus cr\u00e9ditos cinematogr\u00e1ficos incluyen Mientras el Lobo No Est\u00e1 y El Habitante.", "before_fame": "Tom\u00f3 una clase de actuaci\u00f3n de verano en The American Academy of Dramatic Arts.", "curiosities": "Su cuenta de Instagram helloimcarla.a tiene m\u00e1s de 190.000 seguidores. Hace posturas de yoga y las publica en su cuenta.", "family_life": "El nombre de su padre es Frank. Ha sido vinculada sentimentalmente con el cantante\u00a0Alonso Villalpando.", "association": "Martha Higareda\u00a0y ella aparecen en No Manches Frida."}