{"name": "Carmella Rose", "job": "Modelo", "img": "https://www.famousbirthdays.com/faces/rose-carmella-image.jpg", "birth_date": ["10", "3,", "1995"], "birth_place": "California", "about": "Modelo de Wilhelmina que ha aparecido en publicaciones como Maxim y Playboy. Ha ganado mucha popularidad con m\u00e1s de 2.4 millones de seguidores en Instagram.", "before_fame": "En septiembre del 2013 introdujo su cuenta de Twitter con la publicaci\u00f3n \"Hello world! My official twitter account. Let's connect.\"", "curiosities": "Es influenciadora en las redes sociales para la organizaci\u00f3n Models of Compassion.", "family_life": "Su hermana menor se llama Angie. Comenz\u00f3 a salir con el YouTuber\u00a0Juanpa Zurita\u00a0en el 2018.", "association": "Es amiga de la modelo\u00a0Michele Maturo\u00a0y ha publicado fotos con ella en su cuenta de Instagram."}