{"name": "Checo Perezcuadra", "job": "Estrella de Instagram", "img": null, "birth_date": ["10", "4,", "2010"], "birth_place": "M\u00e9xico", "about": "Personalidad de las redes sociales conocida por su contenido de moda, comida y estilo de vida. Comparte viajes a Argentina, Uruguay y Estados Unidos. Ha ganado m\u00e1s de\u00a050.000 seguidores en su cuenta de Instagram\u00a0checoperezcuadra.", "before_fame": "Se uni\u00f3 a Instagram en agosto del 2017.", "curiosities": "En julio del 2022, public\u00f3 fotos de un viaje a Disneyland.", "family_life": "Es de M\u00e9xico.", "association": "En sus videos utiliza canciones como \"Ultra Solo\" de Polima Westcoast y Pailita\u00a0e \"It's Been a Long, Long Time\" de Harry James y Kitty Kallen."}