{"name": "Conor Husting", "job": "Actor de Televisi\u00f3n", "img": null, "birth_date": ["3", "9,", "2000"], "birth_place": "Estados Unidos", "about": "Actor profesional que tuvo un a\u00f1o revelaci\u00f3n en el 2018 despu\u00e9s de conseguir un papel recurrente en la serie\u00a0Prince of Peoria\u00a0de Netflix. M\u00e1s tarde se convirti\u00f3 en miembro regular de la serie The Expanding Universe of Ashley Garc\u00eda en el 2020.", "before_fame": "Su primer papel acreditado fue en la pel\u00edcula Almost Home del 2018.", "curiosities": "Obtuvo un papel en la pel\u00edcula Let Us In del 2020 que tambi\u00e9n present\u00f3 a\u00a0Sadie Stanley\u00a0y\u00a0Mackenzie Ziegler.", "family_life": "Le dese\u00f3 un feliz cumplea\u00f1os a su hermano mayor en Instagram en febrero del 2019.", "association": "Hizo una aparici\u00f3n como invitado en la serie de comedia Man With a Plan de\u00a0Matt LeBlanc\u00a0en el 2019."}