{"name": "Danilis Boom", "job": "Estrella de TikTok", "img": "https://www.famousbirthdays.com/faces/boom-danilis-image.jpg", "birth_date": ["3", "14,", "2002"], "birth_place": "Rusia", "about": "Creador verificado de contenido de TikTok y personalidad de las redes sociales conocido por compartir videos de baile, sincronizaci\u00f3n de labios y parodias en su cuenta danilis_boom. Tiene m\u00e1s de 13 millones de seguidores en la plataforma.", "before_fame": "Hizo su debut en TikTok en un video de finales del 2019 con m\u00fasica del cantautor\u00a0Trevor Daniel.", "curiosities": "Como influenciador de las redes sociales, es miembro del grupo de creadores de contenido XO Team.\u00a0Ha publicado varios videos sobre el exitoso programa de televisi\u00f3n\u00a0Squid Game.", "family_life": "Naci\u00f3 en Rusia.", "association": "En marzo del 2021, \u00e9l y sus amigos realizaron un baile en TikTok con m\u00fasica de\u00a0Charli XCX."}