{"name": "Diana Palomino", "job": "Estrella de Instagram", "img": "https://www.famousbirthdays.com/faces/palomino-diana-image.jpg", "birth_date": ["2", "4", "1987"], "birth_place": "Per\u00fa", "about": "Estrella peruana de Instagram que usualmente modela en fotos en su cuenta dianasanchezpalomino04. Ha acumulado m\u00e1s de 900.000 seguidores en su Instagram.", "before_fame": "Comenz\u00f3 a publicar en su cuenta de Instagram en", "curiosities": "Fue concursante en el concurso de telerrealidad Combate de Per\u00fa.", "family_life": "Es originaria de Per\u00fa. Est\u00e1 saliendo con el influencer Dan Guido.", "association": "Es una modelo peruana popular con una gran cantidad de seguidores en Instagram como\u00a0Denise Schaefer."}