{"name": "Dtay", "job": "Estrella de TikTok", "img": "https://www.famousbirthdays.com/faces/williams-dante-image.jpg", "birth_date": ["2", "4", "1998"], "birth_place": "Estados Unidos", "about": "Personalidad vers\u00e1til de las redes sociales que se llama Dante 'Williams, pero mejor conocido como Dtay. Dirige una popular cuenta de TikTok con el nombre de usuario dtay.known, y publica videos de baile originales, parodias de comedia y mini-vlogs. Ha obtenido m\u00e1s de 16 millones de fan\u00e1ticos.\u00a0Su cuenta de YouTube Dtay Known ha presentado muchos videos populares de parodias de canciones y ha ganado m\u00e1s de 2.1 millones de suscriptores.", "before_fame": "Mucho antes de comenzar a usar TikTok, abri\u00f3 su cuenta de Twitter en abril del 2012.", "curiosities": "Uno de sus videos de TikTok m\u00e1s populares es su respuesta al Desaf\u00edo Tutting titulado \"Desaf\u00edo Tutting Gone Wrong\".\u00a0Public\u00f3 el juego de computadora RAID: Shadow Legends en su canal de YouTube.", "family_life": "Su hermano menor, Devin Williams, tambi\u00e9n es una popular estrella de TikTok.", "association": "Present\u00f3 a su compa\u00f1era estrella de Tiktok TheBlackTrunks en un video de Instagram que comparti\u00f3 en su cuenta en febrero del 2021."}