{"name": "D\u00e1lmata", "job": "Cantante de Reggaet\u00f3n", "img": null, "birth_date": ["2", "27", "1979"], "birth_place": "Ponce,  PR", "about": "Cantante puertorrique\u00f1o y miembro del d\u00fao de reggaeton,\u00a0\u00d1ejo & D\u00e1lmata. Su grupo es conocido por canciones como \"Esa Nena Sonia\" y \"El Abrazo Del Oso.\"", "before_fame": "Su grupo lanz\u00f3 su \u00e1lbum debut, titulado Broke & Famous, en el 2007.", "curiosities": "Ha acumulado m\u00e1s de 100.000 seguidores en Twitter.", "family_life": "Sus padres son Fernando Mangual Almod\u00f3var y Mar\u00eda V\u00e1zquez Rodr\u00edguez.", "association": "\u00d1ejo\u00a0es el otro integrante que lo acompa\u00f1a en el d\u00fao \u00d1ejo & D\u00e1lmata."}