{"name": "Francisco Games", "job": "Estrella de YouTube", "img": null, "birth_date": ["1", "28", "2000"], "birth_place": "M\u00e9xico", "about": "Estrella de YouTube que ha saltado a la fama a trav\u00e9s de su canal autotitulado. Ha recibido m\u00e1s de 635 millones de de reproducciones con sus videos de los videojuegos de\u00a0Minecraft\u00a0y\u00a0Roblox,\u00a0y sus Let's Plays, incluyendo una variedad de mods.", "before_fame": "Lanz\u00f3 su canal de YouTube en diciembre del 2011.", "curiosities": "Su audiencia de YouTube ha crecido a m\u00e1s de 4.5 millones de suscriptores.", "family_life": "Naci\u00f3 y se cri\u00f3 en M\u00e9xico.", "association": "A menudo colabora con\u00a0Mikecrack\u00a0en contenido para YouTube."}