{"name": "Julianne Moore", "job": "Actriz de Cine", "img": "https://www.famousbirthdays.com/faces/moore-julianne-image.jpg", "birth_date": ["12", "3,", "1960"], "birth_place": "Fort Bragg,  NC", "about": "Vers\u00e1til actriz conocida por sus papeles en pel\u00edculas como Boogie Nights, Far From Heaven,\u00a0The Lost World: Jurassic Park\u00a0y\u00a0The Kids Are All Right. Recibi\u00f3 un Premio de la Academia y un Globo de Oro a la Mejor Actriz por su papel en la pel\u00edcula\u00a0Still Alice\u00a0del 2014.", "before_fame": "Estudi\u00f3 Teatro en la Universidad de Boston y tuvo un papel regular en\u00a0As the World Turns.", "curiosities": "Interpret\u00f3 a Maude, una feminista exc\u00e9ntrica y adinerada, en The Big Lebowski.", "family_life": "Se cas\u00f3 con Bart Freundlich en el 2003. Tiene un hijo llamado Caleb y una hija llamada Liv. Estuvo previamente casada con John Gould Rubin de 1986 a 1995.", "association": "Protagoniz\u00f3 The Hours junto a\u00a0Meryl Streep.\u00a0"}