{"name": "LukeDidThat", "job": "Estrella de TikTok", "img": "https://www.famousbirthdays.com/faces/west-luke-image.jpg", "birth_date": ["12", "2,", "2002"], "birth_place": "Utah", "about": "Personalidad de las redes sociales y creador de contenido de TikTok que se hizo famoso por comer diversos alimentos picantes frente a la c\u00e1mara. En junio del 2022, su cuenta fue suspendida. M\u00e1s tarde volvi\u00f3 a TikTok con el nombre de usuario\u00a0luke.did.that.", "before_fame": "En un video anterior, fingi\u00f3 beber su propia orina a petici\u00f3n de un fan\u00e1tico.", "curiosities": "Uno de sus desaf\u00edos de comida picante m\u00e1s populares se volvi\u00f3 viral con m\u00e1s de 118 millones de vistas. Tambi\u00e9n tiene un canal popular en YouTube que ha ganado m\u00e1s de 22 millones de suscriptores. Desde que se uni\u00f3 a YouTube a principios del 2021, ha visto que los videos de su canal han obtenido m\u00e1s de 9.5 mil millones de vistas totales. Tambi\u00e9n ha asumido desaf\u00edos como beber Coca-Cola con caramelos Mentos, as\u00ed como beber bebidas extremadamente \u00e1cidas. Ha tenido varios videos cortos de YouTube con m\u00e1s de 10 millones de vistas, incluyendo algunos videos ASMR.", "family_life": "Su nombre completo es Luke West.", "association": "Cre\u00f3 un TikTok al ritmo de la canci\u00f3n \"Sicko Mode\" del rapero Travis Scott."}