{"name": "Martina Catini", "job": "Estrella de TikTok", "img": null, "birth_date": ["9", "4,", "2004"], "birth_place": "Argentina", "about": "TikToker argentina conocida a trav\u00e9s de su p\u00e1gina marttucatiniii donde ha conseguido m\u00e1s de 3.5 millones de seguidores. Sus TikToks consisten principalmente en clips de baile y videos de lip-sync a veces grabados con sus amigos. Sus TikToks han recibido m\u00e1s de 92 millones de me gusta en total.", "before_fame": "Public\u00f3 su primer TikTok en noviembre del 2019.", "curiosities": "En junio del 2022, public\u00f3 un TikTok en el que le preguntaba a sus espectadores por los deportes que les gustaban. El video ha recibido m\u00e1s de 7.8 millones de visitas.", "family_life": "Naci\u00f3 en Argentina.", "association": "Ella y\u00a0Maru Lee\u00a0son estrellas de TikTok de Argentina."}