{"name": "Michael Schumacher", "job": "Piloto de Carreras", "img": "https://www.famousbirthdays.com/faces/schumacher-michael-image.jpg", "birth_date": ["1", "3,", "1969"], "birth_place": "Hurth,Alemania", "about": "Piloto campe\u00f3n de carreras de la F\u00f3rmula 1 que represent\u00f3 a Ferrari de 1996 al 2006.", "before_fame": "Empez\u00f3 a conducir Kart motorizados a la edad de cuatro a\u00f1os.", "curiosities": "Se convirti\u00f3 en siete veces Campe\u00f3n Mundial de la Formula 1 de 1994 al 2004 y ayud\u00f3 a desarrollar el primer casco ligero del fibra de carb\u00f3n.", "family_life": "Se cas\u00f3 con Corinna Betsch en agosto de 1995. Su hermano menor Ralf Schumacher tambi\u00e9n fue piloto de carreras de la Formula 1. Tiene dos hijos: Mick y Gina-Maria.", "association": "Se vio envuelto en un choque con Damon Hill durante la carrera final de la temporada de 1994 en Adelaide."}