{"name": "Mike Ruga", "job": "Estrella de Instagram", "img": "https://www.famousbirthdays.com/faces/ruga-mike-image.jpg", "birth_date": ["1", "2", "1991"], "birth_place": "Chile", "about": "Estrella de Instagram conocido por su contenido sobre estilo de vida, interacciones humor\u00edsticas con el p\u00fablico, trucos de magia, videos de apariciones en clubes y entrevistas. Comparte su diversa gama de de videos con sus 330.000 seguidores en Instagram. ", "before_fame": "Comenz\u00f3 compartiendo contenido en su Instagram en diciembre del 2014.", "curiosities": "Adem\u00e1s de Instagram, tiene un podcast llamado FREEDOMIND donde habla de m\u00fasica, arte y cultura. ", "family_life": "Naci\u00f3 en Chile pero fue criado en Elizabeth, Nueva Jersey.", "association": "Public\u00f3 un video siendo rechazado en la entrada del club Starlets en Nueva York junto a 6IX9INE."}