{"name": "Natalia Boussart", "job": "Estrella de Instagram", "img": null, "birth_date": ["1", "2", "2003"], "birth_place": "M\u00e9xico", "about": "Estrella de las redes sociales que ha conseguido fama por su cuenta de Instagram auto-titulada. Ha obtenido gran popularidad por su modelaje casual chic frecuentemente a trav\u00e9s de fotoblogueo de aventuras en lugares por todo el mundo.", "before_fame": "Comenz\u00f3 su cuenta de Instagram con su primera publicaci\u00f3n en febrero del 2017.", "curiosities": "Ha visto a su audiencia de Instagram crecer a m\u00e1s de 20.000 seguidores. Apareci\u00f3 como invitada en la serie de TV\u00a0La Rosa de Guadalupe\u00a0en el 2015-2016.", "family_life": "En marzo del 2019 public\u00f3 una foto con su primo Sebasti\u00e1n Ramos Gil en el festival de m\u00fasica Pa'l Norte.", "association": "Nicole Vale\u00a0y ella han aparecido en la serie de TV La Rosa de Guadalupe."}