{"name": "Nick Fosco", "job": "Estrella de Twitch", "img": "https://www.famousbirthdays.com/faces/frosco-nick-image.jpg", "birth_date": ["2", "18", "2003"], "birth_place": "Erie,  PA", "about": "Estrella de Twitch y jugador profesional de\u00a0Fortnite. Se describe a s\u00ed mismo como un estudiante universitario que se mud\u00f3 a Texas para dedicarse a la creaci\u00f3n de contenido. Ha acumulado m\u00e1s de\u00a01.8 millones de seguidores en su cuenta de\u00a0Lacy Live. Se uni\u00f3 a\u00a0FaZe Clan\u00a0en el 2024.", "before_fame": "Se uni\u00f3 a YouTube en mayo del 2020.", "curiosities": "En octubre del 2023, comparti\u00f3 un video de YouTube en el que intent\u00f3 unirse al clan de TikTok m\u00e1s t\u00f3xico. Uno de sus espectadores dijo que quer\u00eda gritar de risa mientras lo ve\u00eda.", "family_life": "Es de los Estados Unidos.", "association": "Sommerset tambi\u00e9n es una estrella de Twitch conocido por transmitir en vivo Fortnite."}