{"name": "PolloFrito", "job": "Estrella de TikTok", "img": "https://www.famousbirthdays.com/faces/pollofrito-image.jpg", "birth_date": ["2", "10", "2003"], "birth_place": "M\u00e9xico", "about": "Personalidad de las redes sociales y creador de contenido de TikTok mejor conocido por su cuenta verificada, el.pollofrito. Crea contenido c\u00f3mico para\u00a0Minecraft\u00a0con su caracter\u00edstico personaje de piel de pollo. Tiene m\u00e1s de 4 millones de seguidores.", "before_fame": "Una de sus primeras publicaciones es el video del 2020, \"Nose si me quedo\". El video est\u00e1 musicalizado por Simple Plan.", "curiosities": "A finales del 2020, su TikTok de Minecraft \"M\u00e1ndaselo a tu amigo sin decir nada xD\" se hizo viral con m\u00e1s de 1 mill\u00f3n de visualizaciones. En el 2023, publica el libro PolloFrito y el ladr\u00f3n de esmeraldas.", "family_life": "Naci\u00f3 en M\u00e9xico.", "association": "Cre\u00f3 un d\u00fao en TikTok con su colega\u00a0That Vegan Teacher."}