{"name": "Rakhee Thakrar", "job": "Actriz de Telenovelas", "img": "https://www.famousbirthdays.com/faces/thakrar-rakhee-image.jpg", "birth_date": ["2", "29", "1984"], "birth_place": "Inglaterra", "about": "Famosa por su papel de Shabnam Masood en la popular telenovela brit\u00e1nica EastEnders, tambi\u00e9n es conocida por sus apariciones en Holby City,\u00a0Sex Education, Doctors y DCI Banks.", "before_fame": "Durante su adolescencia, ella era una artista regular en una compa\u00f1\u00eda de teatro inglesa conocida como Hathi Productions.", "curiosities": "Durante el a\u00f1o 2004, trabaj\u00f3 como periodista para el Leicester Mercury Pathfinder Program.", "family_life": "Naci\u00f3 y se cri\u00f3 en Leicester, Leicestershire, Inglaterra.", "association": "En EastEnders, interpret\u00f3 a la hija del personaje de Nitin Ganatra."}