{"name": "Roberto Palazuelos", "job": "Actor de Televisi\u00f3n", "img": "https://www.famousbirthdays.com/faces/palazuelos-roberto-image.jpg", "birth_date": ["1", "31", "1967"], "birth_place": "Acapulco,M\u00e9xico", "about": "Actor mexicano que ha aparecido en pel\u00edculas como Hasta Que La Boda Nos Separe y Cofrad\u00eda. Interpret\u00f3 el papel de Santiago Sep\u00falveda en la serie de TV Entreolivos.", "before_fame": "Uno de sus primeros papeles actorales fue en la pel\u00edcula Mariana, Mariana de 1987.", "curiosities": "Apareci\u00f3 en 142 episodios de la serie de TV Ma\u00f1ana Es Para Siempre. Viaj\u00f3 a Canc\u00fan, M\u00e9xico en marzo del 2019.", "family_life": "Sus padres son Mar\u00eda Badeaux y Roberto Palazuelos Rosensweit.", "association": "Actu\u00f3 junto a\u00a0Marjorie de Sousa\u00a0en la serie de TV Hasta El Fin Del Mundo."}