{"name": "Sebastian Haack", "job": "Estrella de YouTube", "img": null, "birth_date": ["2", "10,", "1976"], "birth_place": "Espa\u00f1a", "about": "Patriarca del canal de YouTube\u00a0The Crazy Haacks. Vlog de retos familiares y bromas, han acumulado para ellos m\u00e1s de 3.5 millones de suscriptores y 1.5 mil millones de reproducciones totales.", "before_fame": "Su primera aparici\u00f3n en el canal fue el 5 de diciembre del 2015, en un video titulado \"Christmas Holidays 2014: Family Vlogs!\"", "curiosities": "El 15 de octubre del 2017, publicaron un video de competencia de peluquer\u00eda. El desaf\u00edo consist\u00eda en usar una aspiradora como herramienta para el cabello. Uno de sus videos m\u00e1s populares que acumul\u00f3 m\u00e1s de 17 millones de reproducciones en menos de un mes.", "family_life": "Tiene tres hijos con su exesposa\u00a0M\u00f3nica\u00a0llamados\u00a0Mateo,\u00a0Mateo\u00a0y\u00a0Daniela.", "association": "Johnny Tannerites\u00a0es tambi\u00e9n patriarca de una familia en Youtube."}