{"name": "Youngjae", "job": "Cantante Pop", "img": "https://www.famousbirthdays.com/faces/youngjae-image.jpg", "birth_date": ["1", "24", "1994"], "birth_place": "Se\u00fal,Corea del Sur", "about": "Cantante y bailar\u00edn surcoreano conocido por ser uno de los miembros de la banda de K-Pop B.A.P. Tambi\u00e9n es conocido por sencillos como \"Everything is Pretty.\"", "before_fame": "Tuvo sus inicios en la industria del entretenimiento despu\u00e9s de obtener el primer lugar en una audici\u00f3n de JYP.", "curiosities": "Apareci\u00f3 en el video musical de la canci\u00f3n \"Starlight Moonlight\" del grupo surcoreano Secret.", "family_life": "Tiene un hermano mayor.", "association": "\u00c9l y Jung Dae-hyun han sido miembros de B.A.P."}